{"slug":"behavior-therapy","name":"Behavior therapy","yearly":{"2006":{"MM":{"p":10,"c":799,"r":79.9},"MW":{"p":6,"c":373,"r":62.1667},"WM":{"p":12,"c":1372,"r":114.3333},"WW":{"p":7,"c":297,"r":42.4286}},"2007":{"MM":{"p":11,"c":944,"r":85.8182},"MW":{"p":14,"c":1330,"r":95.0},"WM":{"p":4,"c":186,"r":46.5},"WW":{"p":8,"c":311,"r":38.875}},"2008":{"MM":{"p":16,"c":651,"r":40.6875},"MW":{"p":9,"c":650,"r":72.2222},"WM":{"p":9,"c":303,"r":33.6667},"WW":{"p":15,"c":531,"r":35.4}},"2009":{"MM":{"p":2,"c":57,"r":28.5},"MW":{"p":2,"c":153,"r":76.5},"WM":{"p":7,"c":401,"r":57.2857},"WW":{"p":4,"c":124,"r":31.0}},"2010":{"MM":{"p":10,"c":298,"r":29.8},"MW":{"p":11,"c":581,"r":52.8182},"WM":{"p":8,"c":377,"r":47.125},"WW":{"p":13,"c":401,"r":30.8462}},"2011":{"MM":{"p":23,"c":2859,"r":124.3043},"MW":{"p":17,"c":1162,"r":68.3529},"WM":{"p":14,"c":577,"r":41.2143},"WW":{"p":22,"c":897,"r":40.7727}},"2012":{"MM":{"p":12,"c":877,"r":73.0833},"MW":{"p":10,"c":434,"r":43.4},"WM":{"p":6,"c":203,"r":33.8333},"WW":{"p":9,"c":185,"r":20.5556}},"2013":{"MM":{"p":20,"c":1106,"r":55.3},"MW":{"p":7,"c":301,"r":43.0},"WM":{"p":14,"c":381,"r":27.2143},"WW":{"p":8,"c":304,"r":38.0}},"2014":{"MM":{"p":16,"c":1126,"r":70.375},"MW":{"p":10,"c":392,"r":39.2},"WM":{"p":19,"c":628,"r":33.0526},"WW":{"p":12,"c":397,"r":33.0833}},"2015":{"MM":{"p":18,"c":272,"r":15.1111},"MW":{"p":5,"c":239,"r":47.8},"WM":{"p":13,"c":351,"r":27.0},"WW":{"p":14,"c":344,"r":24.5714}},"2016":{"MM":{"p":19,"c":1319,"r":69.4211},"MW":{"p":17,"c":847,"r":49.8235},"WM":{"p":13,"c":442,"r":34.0},"WW":{"p":21,"c":531,"r":25.2857}},"2017":{"MM":{"p":17,"c":453,"r":26.6471},"MW":{"p":10,"c":287,"r":28.7},"WM":{"p":24,"c":602,"r":25.0833},"WW":{"p":18,"c":324,"r":18.0}},"2018":{"MM":{"p":17,"c":395,"r":23.2353},"MW":{"p":9,"c":108,"r":12.0},"WM":{"p":27,"c":468,"r":17.3333},"WW":{"p":18,"c":312,"r":17.3333}},"2019":{"MM":{"p":19,"c":344,"r":18.1053},"MW":{"p":13,"c":282,"r":21.6923},"WM":{"p":20,"c":377,"r":18.85},"WW":{"p":27,"c":508,"r":18.8148}},"2020":{"MM":{"p":14,"c":174,"r":12.4286},"MW":{"p":8,"c":161,"r":20.125},"WM":{"p":26,"c":368,"r":14.1538},"WW":{"p":13,"c":171,"r":13.1538}},"2021":{"MM":{"p":11,"c":101,"r":9.1818},"MW":{"p":14,"c":161,"r":11.5},"WM":{"p":20,"c":173,"r":8.65},"WW":{"p":29,"c":336,"r":11.5862}},"2022":{"MM":{"p":21,"c":150,"r":7.1429},"MW":{"p":10,"c":104,"r":10.4},"WM":{"p":25,"c":207,"r":8.28},"WW":{"p":22,"c":186,"r":8.4545}},"2023":{"MM":{"p":20,"c":114,"r":5.7},"MW":{"p":8,"c":45,"r":5.625},"WM":{"p":26,"c":166,"r":6.3846},"WW":{"p":19,"c":98,"r":5.1579}},"2024":{"MM":{"p":9,"c":32,"r":3.5556},"MW":{"p":7,"c":24,"r":3.4286},"WM":{"p":16,"c":33,"r":2.0625},"WW":{"p":23,"c":28,"r":1.2174}},"2025":{"MM":{"p":7,"c":5,"r":0.7143},"MW":{"p":1,"c":0,"r":0.0},"WM":{"p":10,"c":0,"r":0.0},"WW":{"p":8,"c":7,"r":0.875}}},"citing":{"WW":{"W":3585,"M":1797,"total":5382,"pctW":66.6,"pctM":33.4},"WM":{"W":4596,"M":2655,"total":7251,"pctW":63.4,"pctM":36.6},"MW":{"W":4244,"M":2700,"total":6944,"pctW":61.1,"pctM":38.9},"MM":{"W":6122,"M":4927,"total":11049,"pctW":55.4,"pctM":44.6}},"rolling_if":{"2007":{"WW":{"p":8,"c":8,"if":1.0,"norm":0.7143},"WM":{"p":13,"c":33,"if":2.538,"norm":1.8129},"MW":{"p":6,"c":8,"if":1.333,"norm":0.9521},"MM":{"p":10,"c":14,"if":1.4,"norm":1.0}},"2008":{"WW":{"p":15,"c":17,"if":1.133,"norm":0.4326},"WM":{"p":16,"c":55,"if":3.438,"norm":1.3127},"MW":{"p":20,"c":41,"if":2.05,"norm":0.7827},"MM":{"p":21,"c":55,"if":2.619,"norm":1.0}},"2009":{"WW":{"p":23,"c":22,"if":0.957,"norm":0.4455},"WM":{"p":13,"c":16,"if":1.231,"norm":0.5731},"MW":{"p":23,"c":40,"if":1.739,"norm":0.8096},"MM":{"p":27,"c":58,"if":2.148,"norm":1.0}},"2010":{"WW":{"p":19,"c":40,"if":2.105,"norm":0.7577},"WM":{"p":16,"c":25,"if":1.562,"norm":0.5623},"MW":{"p":11,"c":11,"if":1.0,"norm":0.36},"MM":{"p":18,"c":50,"if":2.778,"norm":1.0}},"2011":{"WW":{"p":17,"c":22,"if":1.294,"norm":0.7059},"WM":{"p":15,"c":43,"if":2.867,"norm":1.5641},"MW":{"p":13,"c":31,"if":2.385,"norm":1.3011},"MM":{"p":12,"c":22,"if":1.833,"norm":1.0}},"2012":{"WW":{"p":35,"c":51,"if":1.457,"norm":0.641},"WM":{"p":22,"c":49,"if":2.227,"norm":0.9798},"MW":{"p":28,"c":50,"if":1.786,"norm":0.7857},"MM":{"p":33,"c":75,"if":2.273,"norm":1.0}},"2013":{"WW":{"p":31,"c":47,"if":1.516,"norm":0.2964},"WM":{"p":20,"c":52,"if":2.6,"norm":0.5084},"MW":{"p":27,"c":54,"if":2.0,"norm":0.3911},"MM":{"p":35,"c":179,"if":5.114,"norm":1.0}},"2014":{"WW":{"p":17,"c":35,"if":2.059,"norm":0.5314},"WM":{"p":20,"c":35,"if":1.75,"norm":0.4516},"MW":{"p":17,"c":64,"if":3.765,"norm":0.9716},"MM":{"p":32,"c":124,"if":3.875,"norm":1.0}},"2015":{"WW":{"p":20,"c":62,"if":3.1,"norm":0.7914},"WM":{"p":33,"c":79,"if":2.394,"norm":0.6112},"MW":{"p":17,"c":51,"if":3.0,"norm":0.7659},"MM":{"p":36,"c":141,"if":3.917,"norm":1.0}},"2016":{"WW":{"p":26,"c":52,"if":2.0,"norm":0.7313},"WM":{"p":32,"c":89,"if":2.781,"norm":1.0168},"MW":{"p":15,"c":53,"if":3.533,"norm":1.2918},"MM":{"p":34,"c":93,"if":2.735,"norm":1.0}},"2017":{"WW":{"p":35,"c":68,"if":1.943,"norm":0.8768},"WM":{"p":26,"c":62,"if":2.385,"norm":1.0763},"MW":{"p":22,"c":53,"if":2.409,"norm":1.0871},"MM":{"p":37,"c":82,"if":2.216,"norm":1.0}},"2018":{"WW":{"p":39,"c":72,"if":1.846,"norm":0.496},"WM":{"p":37,"c":77,"if":2.081,"norm":0.5591},"MW":{"p":27,"c":77,"if":2.852,"norm":0.7663},"MM":{"p":36,"c":134,"if":3.722,"norm":1.0}},"2019":{"WW":{"p":36,"c":54,"if":1.5,"norm":0.7184},"WM":{"p":51,"c":99,"if":1.941,"norm":0.9296},"MW":{"p":19,"c":35,"if":1.842,"norm":0.8822},"MM":{"p":34,"c":71,"if":2.088,"norm":1.0}},"2020":{"WW":{"p":45,"c":94,"if":2.089,"norm":0.917},"WM":{"p":47,"c":105,"if":2.234,"norm":0.9807},"MW":{"p":22,"c":40,"if":1.818,"norm":0.7981},"MM":{"p":36,"c":82,"if":2.278,"norm":1.0}},"2021":{"WW":{"p":40,"c":104,"if":2.6,"norm":1.0591},"WM":{"p":46,"c":100,"if":2.174,"norm":0.8855},"MW":{"p":21,"c":71,"if":3.381,"norm":1.3772},"MM":{"p":33,"c":81,"if":2.455,"norm":1.0}},"2022":{"WW":{"p":42,"c":78,"if":1.857,"norm":0.8145},"WM":{"p":46,"c":97,"if":2.109,"norm":0.925},"MW":{"p":22,"c":45,"if":2.045,"norm":0.8969},"MM":{"p":25,"c":57,"if":2.28,"norm":1.0}},"2023":{"WW":{"p":51,"c":117,"if":2.294,"norm":1.359},"WM":{"p":45,"c":95,"if":2.111,"norm":1.2506},"MW":{"p":24,"c":67,"if":2.792,"norm":1.654},"MM":{"p":32,"c":54,"if":1.688,"norm":1.0}},"2024":{"WW":{"p":41,"c":112,"if":2.732,"norm":1.1915},"WM":{"p":51,"c":118,"if":2.314,"norm":1.0092},"MW":{"p":18,"c":51,"if":2.833,"norm":1.2355},"MM":{"p":41,"c":94,"if":2.293,"norm":1.0}}}}