{"slug":"tropical-life-sciences-research","name":"Tropical life sciences research","yearly":{"2023":{"MM":{"p":2,"c":2,"r":1.0},"MW":{"p":1,"c":1,"r":1.0},"WM":{"p":4,"c":1,"r":0.25},"WW":{"p":3,"c":3,"r":1.0}},"2025":{"MM":{"p":6,"c":2,"r":0.3333},"WM":{"p":5,"c":0,"r":0.0}}},"citing":{"WW":{"W":14,"M":17,"total":31,"pctW":45.2,"pctM":54.8},"WM":{"W":9,"M":5,"total":14,"pctW":64.3,"pctM":35.7},"MW":{"W":9,"M":13,"total":22,"pctW":40.9,"pctM":59.1},"MM":{"W":23,"M":26,"total":49,"pctW":46.9,"pctM":53.1}},"rolling_if":{"2011":{"WW":{"p":0,"c":0,"if":0,"norm":null},"WM":{"p":0,"c":0,"if":0,"norm":null},"MW":{"p":2,"c":0,"if":0.0,"norm":0.0},"MM":{"p":3,"c":1,"if":0.333,"norm":1.0}},"2012":{"WW":{"p":3,"c":0,"if":0.0,"norm":null},"WM":{"p":0,"c":0,"if":0,"norm":null},"MW":{"p":3,"c":3,"if":1.0,"norm":null},"MM":{"p":4,"c":0,"if":0.0,"norm":null}},"2013":{"WW":{"p":4,"c":1,"if":0.25,"norm":null},"WM":{"p":0,"c":0,"if":0,"norm":null},"MW":{"p":1,"c":0,"if":0.0,"norm":null},"MM":{"p":3,"c":0,"if":0.0,"norm":null}},"2014":{"WW":{"p":2,"c":0,"if":0.0,"norm":null},"WM":{"p":1,"c":0,"if":0.0,"norm":null},"MW":{"p":0,"c":0,"if":0,"norm":null},"MM":{"p":2,"c":0,"if":0.0,"norm":null}},"2015":{"WW":{"p":3,"c":0,"if":0.0,"norm":null},"WM":{"p":2,"c":1,"if":0.5,"norm":null},"MW":{"p":0,"c":0,"if":0,"norm":null},"MM":{"p":2,"c":0,"if":0.0,"norm":null}},"2016":{"WW":{"p":2,"c":0,"if":0.0,"norm":null},"WM":{"p":1,"c":0,"if":0.0,"norm":null},"MW":{"p":0,"c":0,"if":0,"norm":null},"MM":{"p":4,"c":0,"if":0.0,"norm":null}},"2017":{"WW":{"p":2,"c":0,"if":0.0,"norm":0.0},"WM":{"p":4,"c":0,"if":0.0,"norm":0.0},"MW":{"p":1,"c":0,"if":0.0,"norm":0.0},"MM":{"p":3,"c":1,"if":0.333,"norm":1.0}},"2018":{"WW":{"p":2,"c":0,"if":0.0,"norm":null},"WM":{"p":5,"c":0,"if":0.0,"norm":null},"MW":{"p":1,"c":0,"if":0.0,"norm":null},"MM":{"p":2,"c":0,"if":0.0,"norm":null}},"2019":{"WW":{"p":1,"c":0,"if":0.0,"norm":0.0},"WM":{"p":3,"c":0,"if":0.0,"norm":0.0},"MW":{"p":0,"c":0,"if":0,"norm":null},"MM":{"p":3,"c":1,"if":0.333,"norm":1.0}},"2020":{"WW":{"p":1,"c":1,"if":1.0,"norm":2.0},"WM":{"p":4,"c":0,"if":0.0,"norm":0.0},"MW":{"p":1,"c":0,"if":0.0,"norm":0.0},"MM":{"p":2,"c":1,"if":0.5,"norm":1.0}},"2021":{"WW":{"p":0,"c":0,"if":0,"norm":null},"WM":{"p":4,"c":3,"if":0.75,"norm":2.2523},"MW":{"p":1,"c":0,"if":0.0,"norm":0.0},"MM":{"p":3,"c":1,"if":0.333,"norm":1.0}},"2022":{"WW":{"p":1,"c":0,"if":0.0,"norm":0.0},"WM":{"p":4,"c":3,"if":0.75,"norm":2.2523},"MW":{"p":2,"c":0,"if":0.0,"norm":0.0},"MM":{"p":3,"c":1,"if":0.333,"norm":1.0}},"2023":{"WW":{"p":1,"c":0,"if":0.0,"norm":0.0},"WM":{"p":2,"c":0,"if":0.0,"norm":0.0},"MW":{"p":2,"c":2,"if":1.0,"norm":3.003},"MM":{"p":3,"c":1,"if":0.333,"norm":1.0}},"2024":{"WW":{"p":3,"c":0,"if":0.0,"norm":0.0},"WM":{"p":4,"c":0,"if":0.0,"norm":0.0},"MW":{"p":1,"c":0,"if":0.0,"norm":0.0},"MM":{"p":4,"c":3,"if":0.75,"norm":1.0}}}}